uart/uart_tx/src/uart_tx.vhd
library IEEE;
use IEEE.std_logic_1164.ALL;


entity uart_tx is 
generic(
    c_clkfreq   : integer := 100_000_000;
    c_baudrate  : integer := 115_200;
    c_stopbit   : integer := 2
);
port (
    clk             : in std_logic;
    data_i          : in std_logic_vector(7 downto 0);
    tx_start_i      : in std_logic;
    tx_o            : out std_logic;
    tx_done_tick    : out std_logic
);
end uart_tx;

architecture behavioral of uart_tx is 

constant c_bittimerlim  : integer := c_clkfreq/c_baudrate;
constant c_stopbitlim   : integer := (c_clkfreq/c_baudrate)*c_stopbit;

type states is (S_IDLE, S_START, S_DATA, S_STOP);
signal state : states := S_IDLE;

signal bittimer : integer range 0 to c_stopbitlim := 0;
signal bitcntr : integer range 0 to 7 := 0;
signal shreg	: std_logic_vector (7 downto 0) := (others => '0');


begin

    P_MAIN : process(clk) begin 
    if(rising_edge(clk)) then 

        case state is 
            when S_IDLE =>
                tx_o			<= '1';
                tx_done_tick	<= '0';
                bitcntr			<= 0;

                if (tx_start_i = '1') then
                    state <= S_START;
                    tx_o <= '0';
                    shreg <= data_i;
                    bittimer <= 0;
                end if;
            
            when S_START =>
                
                if(bittimer = c_bittimerlim -1) then
                    state <= S_DATA;
                    tx_o <= shreg(0);
                    shreg(7)			<= shreg(0);
                    shreg(6 downto 0)	<= shreg(7 downto 1);
                    bittimer <= 0;
                else 
                    bittimer <= bittimer + 1;
                end if;

            when S_DATA =>

                if(bitcntr = 7) then 
                    if(bittimer = c_bittimerlim - 1) then
                        bitcntr <= 0;
                        state <= S_STOP;
                        tx_o <= '1';
                        bittimer <= 0;
                    else 
                        bittimer <= bittimer + 1;
                    end if;
                else 
                    if (bittimer = c_bittimerlim - 1) then
                        bitcntr <= bitcntr + 1;
                        shreg(7)			<= shreg(0);
                        shreg(6 downto 0)	<= shreg(7 downto 1);					
                        tx_o <= shreg(0);
                        bittimer <= 0;
                    else 
                        bittimer <= bittimer + 1;
                    end if;
                end if;

            when S_STOP =>
                if(bittimer = c_stopbitlim  - 1) then 
                    state <= S_IDLE;
                    tx_done_tick <= '1';
                    bittimer <= 0;
                else 
                    bittimer <= bittimer + 1;
                end if;

        end case;

    end if;
    end process;

end behavioral;

uart/uart_tx/src/tb_uart_tx.vhd
library IEEE;
use IEEE.STD_LOGIC_1164.ALL;


entity tb_uart_tx is
generic (
c_clkfreq		: integer := 100_000_000;
c_baudrate		: integer := 10_000_000;
c_stopbit		: integer := 2
);
end tb_uart_tx;

architecture Behavioral of tb_uart_tx is

-- component uart_tx is
-- generic (
--     c_clkfreq		: integer := 27_000_000;
--     c_baudrate		: integer := 115_200;
--     c_stopbit		: integer := 2
-- );
-- port (
--     clk				: in std_logic;
--     data_i			: in std_logic_vector (7 downto 0);
--     tx_start_i		: in std_logic;
--     tx_o			: out std_logic;
--     tx_done_tick	: out std_logic
-- );
-- end component;

signal clk				: std_logic := '0';
signal data_i			: std_logic_vector (7 downto 0) := (others => '0');
signal tx_start_i		: std_logic := '0';
signal tx_o				: std_logic;
signal tx_done_tick	: std_logic;

constant c_clkperiod	: time := 10 ns; -- 27Mhz

begin

DUT : entity work.uart_tx
generic map(
    c_clkfreq		=> c_clkfreq,
    c_baudrate		=> c_baudrate,
    c_stopbit		=> c_stopbit	
)
port map(
    clk				=> clk,
    data_i			=> data_i ,
    tx_start_i		=> tx_start_i,
    tx_o			=> tx_o,
    tx_done_tick	=> tx_done_tick	
);


P_CLKGEN : process begin

clk	<= '0';
wait for c_clkperiod/2;
clk	<= '1';
wait for c_clkperiod/2;

end process P_CLKGEN;

P_STIMULI : process begin

data_i			<= x"00";
tx_start_i		<= '0';

wait for c_clkperiod*10;

data_i		<= "10101010";
tx_start_i	<= '1';
wait for c_clkperiod;
tx_start_i	<= '0';

wait for 1.2 us;

data_i		<= x"A3";
tx_start_i	<= '1';
wait for c_clkperiod;
tx_start_i	<= '0';

wait until (rising_edge(tx_done_tick));

wait for 1 us;

assert false
report "SIM DONE"
severity failure;


end process P_STIMULI;


end Behavioral;

uart/uart_tx/src/uart_tx.vcd
$date
  Tue Jan 27 19:17:57 2026
$end
$version
  GHDL v0
$end
$timescale
  1 fs
$end
$scope module standard $end
$upscope $end
$scope module std_logic_1164 $end
$upscope $end
$scope module tb_uart_tx $end
$var reg 1 ! clk $end
$var reg 8 " data_i[7:0] $end
$var reg 1 # tx_start_i $end
$var reg 1 $ tx_o $end
$var reg 1 % tx_done_tick $end
$scope module dut $end
$var reg 1 & clk $end
$var reg 8 ' data_i[7:0] $end
$var reg 1 ( tx_start_i $end
$var reg 1 ) tx_o $end
$var reg 1 * tx_done_tick $end
$comment state is not handled $end
$var integer 32 + bittimer $end
$var integer 32 , bitcntr $end
$var reg 8 - shreg[7:0] $end
$upscope $end
$upscope $end
$enddefinitions $end
#0
0!
b00000000 "
0#
U$
U%
0&
b00000000 '
0(
U)
U*
b0 +
b0 ,
b00000000 -
#5000000
1!
1$
0%
1&
1)
0*
#10000000
0!
0&
#15000000
1!
1&
#20000000
0!
0&
#25000000
1!
1&
#30000000
0!
0&
#35000000
1!
1&
#40000000
0!
0&
#45000000
1!
1&
#50000000
0!
0&
#55000000
1!
1&
#60000000
0!
0&
#65000000
1!
1&
#70000000
0!
0&
#75000000
1!
1&
#80000000
0!
0&
#85000000
1!
1&
#90000000
0!
0&
#95000000
1!
1&
#100000000
0!
b10101010 "
1#
0&
b10101010 '
1(
#105000000
1!
0$
1&
0)
b10101010 -
#110000000
0!
0#
0&
0(
#115000000
1!
1&
b1 +
#120000000
0!
0&
#125000000
1!
1&
b10 +
#130000000
0!
0&
#135000000
1!
1&
b11 +
#140000000
0!
0&
#145000000
1!
1&
b100 +
#150000000
0!
0&
#155000000
1!
1&
b101 +
#160000000
0!
0&
#165000000
1!
1&
b110 +
#170000000
0!
0&
#175000000
1!
1&
b111 +
#180000000
0!
0&
#185000000
1!
1&
b1000 +
#190000000
0!
0&
#195000000
1!
1&
b1001 +
#200000000
0!
0&
#205000000
1!
1&
b0 +
b01010101 -
#210000000
0!
0&
#215000000
1!
1&
b1 +
#220000000
0!
0&
#225000000
1!
1&
b10 +
#230000000
0!
0&
#235000000
1!
1&
b11 +
#240000000
0!
0&
#245000000
1!
1&
b100 +
#250000000
0!
0&
#255000000
1!
1&
b101 +
#260000000
0!
0&
#265000000
1!
1&
b110 +
#270000000
0!
0&
#275000000
1!
1&
b111 +
#280000000
0!
0&
#285000000
1!
1&
b1000 +
#290000000
0!
0&
#295000000
1!
1&
b1001 +
#300000000
0!
0&
#305000000
1!
1$
1&
1)
b0 +
b1 ,
b10101010 -
#310000000
0!
0&
#315000000
1!
1&
b1 +
#320000000
0!
0&
#325000000
1!
1&
b10 +
#330000000
0!
0&
#335000000
1!
1&
b11 +
#340000000
0!
0&
#345000000
1!
1&
b100 +
#350000000
0!
0&
#355000000
1!
1&
b101 +
#360000000
0!
0&
#365000000
1!
1&
b110 +
#370000000
0!
0&
#375000000
1!
1&
b111 +
#380000000
0!
0&
#385000000
1!
1&
b1000 +
#390000000
0!
0&
#395000000
1!
1&
b1001 +
#400000000
0!
0&
#405000000
1!
0$
1&
0)
b0 +
b10 ,
b01010101 -
#410000000
0!
0&
#415000000
1!
1&
b1 +
#420000000
0!
0&
#425000000
1!
1&
b10 +
#430000000
0!
0&
#435000000
1!
1&
b11 +
#440000000
0!
0&
#445000000
1!
1&
b100 +
#450000000
0!
0&
#455000000
1!
1&
b101 +
#460000000
0!
0&
#465000000
1!
1&
b110 +
#470000000
0!
0&
#475000000
1!
1&
b111 +
#480000000
0!
0&
#485000000
1!
1&
b1000 +
#490000000
0!
0&
#495000000
1!
1&
b1001 +
#500000000
0!
0&
#505000000
1!
1$
1&
1)
b0 +
b11 ,
b10101010 -
#510000000
0!
0&
#515000000
1!
1&
b1 +
#520000000
0!
0&
#525000000
1!
1&
b10 +
#530000000
0!
0&
#535000000
1!
1&
b11 +
#540000000
0!
0&
#545000000
1!
1&
b100 +
#550000000
0!
0&
#555000000
1!
1&
b101 +
#560000000
0!
0&
#565000000
1!
1&
b110 +
#570000000
0!
0&
#575000000
1!
1&
b111 +
#580000000
0!
0&
#585000000
1!
1&
b1000 +
#590000000
0!
0&
#595000000
1!
1&
b1001 +
#600000000
0!
0&
#605000000
1!
0$
1&
0)
b0 +
b100 ,
b01010101 -
#610000000
0!
0&
#615000000
1!
1&
b1 +
#620000000
0!
0&
#625000000
1!
1&
b10 +
#630000000
0!
0&
#635000000
1!
1&
b11 +
#640000000
0!
0&
#645000000
1!
1&
b100 +
#650000000
0!
0&
#655000000
1!
1&
b101 +
#660000000
0!
0&
#665000000
1!
1&
b110 +
#670000000
0!
0&
#675000000
1!
1&
b111 +
#680000000
0!
0&
#685000000
1!
1&
b1000 +
#690000000
0!
0&
#695000000
1!
1&
b1001 +
#700000000
0!
0&
#705000000
1!
1$
1&
1)
b0 +
b101 ,
b10101010 -
#710000000
0!
0&
#715000000
1!
1&
b1 +
#720000000
0!
0&
#725000000
1!
1&
b10 +
#730000000
0!
0&
#735000000
1!
1&
b11 +
#740000000
0!
0&
#745000000
1!
1&
b100 +
#750000000
0!
0&
#755000000
1!
1&
b101 +
#760000000
0!
0&
#765000000
1!
1&
b110 +
#770000000
0!
0&
#775000000
1!
1&
b111 +
#780000000
0!
0&
#785000000
1!
1&
b1000 +
#790000000
0!
0&
#795000000
1!
1&
b1001 +
#800000000
0!
0&
#805000000
1!
0$
1&
0)
b0 +
b110 ,
b01010101 -
#810000000
0!
0&
#815000000
1!
1&
b1 +
#820000000
0!
0&
#825000000
1!
1&
b10 +
#830000000
0!
0&
#835000000
1!
1&
b11 +
#840000000
0!
0&
#845000000
1!
1&
b100 +
#850000000
0!
0&
#855000000
1!
1&
b101 +
#860000000
0!
0&
#865000000
1!
1&
b110 +
#870000000
0!
0&
#875000000
1!
1&
b111 +
#880000000
0!
0&
#885000000
1!
1&
b1000 +
#890000000
0!
0&
#895000000
1!
1&
b1001 +
#900000000
0!
0&
#905000000
1!
1$
1&
1)
b0 +
b111 ,
b10101010 -
#910000000
0!
0&
#915000000
1!
1&
b1 +
#920000000
0!
0&
#925000000
1!
1&
b10 +
#930000000
0!
0&
#935000000
1!
1&
b11 +
#940000000
0!
0&
#945000000
1!
1&
b100 +
#950000000
0!
0&
#955000000
1!
1&
b101 +
#960000000
0!
0&
#965000000
1!
1&
b110 +
#970000000
0!
0&
#975000000
1!
1&
b111 +
#980000000
0!
0&
#985000000
1!
1&
b1000 +
#990000000
0!
0&
#995000000
1!
1&
b1001 +
#1000000000
0!
0&
#1005000000
1!
1&
b0 +
b0 ,
#1010000000
0!
0&
#1015000000
1!
1&
b1 +
#1020000000
0!
0&
#1025000000
1!
1&
b10 +
#1030000000
0!
0&
#1035000000
1!
1&
b11 +
#1040000000
0!
0&
#1045000000
1!
1&
b100 +
#1050000000
0!
0&
#1055000000
1!
1&
b101 +
#1060000000
0!
0&
#1065000000
1!
1&
b110 +
#1070000000
0!
0&
#1075000000
1!
1&
b111 +
#1080000000
0!
0&
#1085000000
1!
1&
b1000 +
#1090000000
0!
0&
#1095000000
1!
1&
b1001 +
#1100000000
0!
0&
#1105000000
1!
1&
b1010 +
#1110000000
0!
0&
#1115000000
1!
1&
b1011 +
#1120000000
0!
0&
#1125000000
1!
1&
b1100 +
#1130000000
0!
0&
#1135000000
1!
1&
b1101 +
#1140000000
0!
0&
#1145000000
1!
1&
b1110 +
#1150000000
0!
0&
#1155000000
1!
1&
b1111 +
#1160000000
0!
0&
#1165000000
1!
1&
b10000 +
#1170000000
0!
0&
#1175000000
1!
1&
b10001 +
#1180000000
0!
0&
#1185000000
1!
1&
b10010 +
#1190000000
0!
0&
#1195000000
1!
1&
b10011 +
#1200000000
0!
0&
#1205000000
1!
1%
1&
1*
b0 +
#1210000000
0!
0&
#1215000000
1!
0%
1&
0*
#1220000000
0!
0&
#1225000000
1!
1&
#1230000000
0!
0&
#1235000000
1!
1&
#1240000000
0!
0&
#1245000000
1!
1&
#1250000000
0!
0&
#1255000000
1!
1&
#1260000000
0!
0&
#1265000000
1!
1&
#1270000000
0!
0&
#1275000000
1!
1&
#1280000000
0!
0&
#1285000000
1!
1&
#1290000000
0!
0&
#1295000000
1!
1&
#1300000000
0!
0&
#1305000000
1!
1&
#1310000000
0!
b10100011 "
1#
0&
b10100011 '
1(
#1315000000
1!
0$
1&
0)
b10100011 -
#1320000000
0!
0#
0&
0(
#1325000000
1!
1&
b1 +
#1330000000
0!
0&
#1335000000
1!
1&
b10 +
#1340000000
0!
0&
#1345000000
1!
1&
b11 +
#1350000000
0!
0&
#1355000000
1!
1&
b100 +
#1360000000
0!
0&
#1365000000
1!
1&
b101 +
#1370000000
0!
0&
#1375000000
1!
1&
b110 +
#1380000000
0!
0&
#1385000000
1!
1&
b111 +
#1390000000
0!
0&
#1395000000
1!
1&
b1000 +
#1400000000
0!
0&
#1405000000
1!
1&
b1001 +
#1410000000
0!
0&
#1415000000
1!
1$
1&
1)
b0 +
b11010001 -
#1420000000
0!
0&
#1425000000
1!
1&
b1 +
#1430000000
0!
0&
#1435000000
1!
1&
b10 +
#1440000000
0!
0&
#1445000000
1!
1&
b11 +
#1450000000
0!
0&
#1455000000
1!
1&
b100 +
#1460000000
0!
0&
#1465000000
1!
1&
b101 +
#1470000000
0!
0&
#1475000000
1!
1&
b110 +
#1480000000
0!
0&
#1485000000
1!
1&
b111 +
#1490000000
0!
0&
#1495000000
1!
1&
b1000 +
#1500000000
0!
0&
#1505000000
1!
1&
b1001 +
#1510000000
0!
0&
#1515000000
1!
1&
b0 +
b1 ,
b11101000 -
#1520000000
0!
0&
#1525000000
1!
1&
b1 +
#1530000000
0!
0&
#1535000000
1!
1&
b10 +
#1540000000
0!
0&
#1545000000
1!
1&
b11 +
#1550000000
0!
0&
#1555000000
1!
1&
b100 +
#1560000000
0!
0&
#1565000000
1!
1&
b101 +
#1570000000
0!
0&
#1575000000
1!
1&
b110 +
#1580000000
0!
0&
#1585000000
1!
1&
b111 +
#1590000000
0!
0&
#1595000000
1!
1&
b1000 +
#1600000000
0!
0&
#1605000000
1!
1&
b1001 +
#1610000000
0!
0&
#1615000000
1!
0$
1&
0)
b0 +
b10 ,
b01110100 -
#1620000000
0!
0&
#1625000000
1!
1&
b1 +
#1630000000
0!
0&
#1635000000
1!
1&
b10 +
#1640000000
0!
0&
#1645000000
1!
1&
b11 +
#1650000000
0!
0&
#1655000000
1!
1&
b100 +
#1660000000
0!
0&
#1665000000
1!
1&
b101 +
#1670000000
0!
0&
#1675000000
1!
1&
b110 +
#1680000000
0!
0&
#1685000000
1!
1&
b111 +
#1690000000
0!
0&
#1695000000
1!
1&
b1000 +
#1700000000
0!
0&
#1705000000
1!
1&
b1001 +
#1710000000
0!
0&
#1715000000
1!
1&
b0 +
b11 ,
b00111010 -
#1720000000
0!
0&
#1725000000
1!
1&
b1 +
#1730000000
0!
0&
#1735000000
1!
1&
b10 +
#1740000000
0!
0&
#1745000000
1!
1&
b11 +
#1750000000
0!
0&
#1755000000
1!
1&
b100 +
#1760000000
0!
0&
#1765000000
1!
1&
b101 +
#1770000000
0!
0&
#1775000000
1!
1&
b110 +
#1780000000
0!
0&
#1785000000
1!
1&
b111 +
#1790000000
0!
0&
#1795000000
1!
1&
b1000 +
#1800000000
0!
0&
#1805000000
1!
1&
b1001 +
#1810000000
0!
0&
#1815000000
1!
1&
b0 +
b100 ,
b00011101 -
#1820000000
0!
0&
#1825000000
1!
1&
b1 +
#1830000000
0!
0&
#1835000000
1!
1&
b10 +
#1840000000
0!
0&
#1845000000
1!
1&
b11 +
#1850000000
0!
0&
#1855000000
1!
1&
b100 +
#1860000000
0!
0&
#1865000000
1!
1&
b101 +
#1870000000
0!
0&
#1875000000
1!
1&
b110 +
#1880000000
0!
0&
#1885000000
1!
1&
b111 +
#1890000000
0!
0&
#1895000000
1!
1&
b1000 +
#1900000000
0!
0&
#1905000000
1!
1&
b1001 +
#1910000000
0!
0&
#1915000000
1!
1$
1&
1)
b0 +
b101 ,
b10001110 -
#1920000000
0!
0&
#1925000000
1!
1&
b1 +
#1930000000
0!
0&
#1935000000
1!
1&
b10 +
#1940000000
0!
0&
#1945000000
1!
1&
b11 +
#1950000000
0!
0&
#1955000000
1!
1&
b100 +
#1960000000
0!
0&
#1965000000
1!
1&
b101 +
#1970000000
0!
0&
#1975000000
1!
1&
b110 +
#1980000000
0!
0&
#1985000000
1!
1&
b111 +
#1990000000
0!
0&
#1995000000
1!
1&
b1000 +
#2000000000
0!
0&
#2005000000
1!
1&
b1001 +
#2010000000
0!
0&
#2015000000
1!
0$
1&
0)
b0 +
b110 ,
b01000111 -
#2020000000
0!
0&
#2025000000
1!
1&
b1 +
#2030000000
0!
0&
#2035000000
1!
1&
b10 +
#2040000000
0!
0&
#2045000000
1!
1&
b11 +
#2050000000
0!
0&
#2055000000
1!
1&
b100 +
#2060000000
0!
0&
#2065000000
1!
1&
b101 +
#2070000000
0!
0&
#2075000000
1!
1&
b110 +
#2080000000
0!
0&
#2085000000
1!
1&
b111 +
#2090000000
0!
0&
#2095000000
1!
1&
b1000 +
#2100000000
0!
0&
#2105000000
1!
1&
b1001 +
#2110000000
0!
0&
#2115000000
1!
1$
1&
1)
b0 +
b111 ,
b10100011 -
#2120000000
0!
0&
#2125000000
1!
1&
b1 +
#2130000000
0!
0&
#2135000000
1!
1&
b10 +
#2140000000
0!
0&
#2145000000
1!
1&
b11 +
#2150000000
0!
0&
#2155000000
1!
1&
b100 +
#2160000000
0!
0&
#2165000000
1!
1&
b101 +
#2170000000
0!
0&
#2175000000
1!
1&
b110 +
#2180000000
0!
0&
#2185000000
1!
1&
b111 +
#2190000000
0!
0&
#2195000000
1!
1&
b1000 +
#2200000000
0!
0&
#2205000000
1!
1&
b1001 +
#2210000000
0!
0&
#2215000000
1!
1&
b0 +
b0 ,
#2220000000
0!
0&
#2225000000
1!
1&
b1 +
#2230000000
0!
0&
#2235000000
1!
1&
b10 +
#2240000000
0!
0&
#2245000000
1!
1&
b11 +
#2250000000
0!
0&
#2255000000
1!
1&
b100 +
#2260000000
0!
0&
#2265000000
1!
1&
b101 +
#2270000000
0!
0&
#2275000000
1!
1&
b110 +
#2280000000
0!
0&
#2285000000
1!
1&
b111 +
#2290000000
0!
0&
#2295000000
1!
1&
b1000 +
#2300000000
0!
0&
#2305000000
1!
1&
b1001 +
#2310000000
0!
0&
#2315000000
1!
1&
b1010 +
#2320000000
0!
0&
#2325000000
1!
1&
b1011 +
#2330000000
0!
0&
#2335000000
1!
1&
b1100 +
#2340000000
0!
0&
#2345000000
1!
1&
b1101 +
#2350000000
0!
0&
#2355000000
1!
1&
b1110 +
#2360000000
0!
0&
#2365000000
1!
1&
b1111 +
#2370000000
0!
0&
#2375000000
1!
1&
b10000 +
#2380000000
0!
0&
#2385000000
1!
1&
b10001 +
#2390000000
0!
0&
#2395000000
1!
1&
b10010 +
#2400000000
0!
0&
#2405000000
1!
1&
b10011 +
#2410000000
0!
0&
#2415000000
1!
1%
1&
1*
b0 +
#2420000000
0!
0&
#2425000000
1!
0%
1&
0*
