uart/uart_rx/src/uart_rx.vhd
library IEEE;
use IEEE.std_logic_1164.ALL;


entity uart_rx is
generic(
    c_clkfreq   : integer := 100_000_000;
    c_baudrate  : integer := 115_200
);
port(
    clk             : in std_logic;
    rx_i            : in std_logic;
    data_o          : out std_logic_vector(7 downto 0);
    rx_done_tick_o  : out std_logic
);
end uart_rx;


architecture Behavioral of uart_rx is

    constant c_bittimerlim : integer := c_clkfreq/c_baudrate;

    type states is (S_IDLE, S_START, S_DATA, S_STOP);
    signal state : states := S_IDLE;

    signal bittimer : integer range 0 to c_bittimerlim := 0;
    signal bitcntr  : integer range 0 to 7 := 0;
    signal shreg    : std_logic_vector (7 downto 0) := (others => '0');

begin

P_MAIN : process(clk) begin 

    if(rising_edge(clk)) then 
    
    case state is
        when S_IDLE => 
            rx_done_tick_o <= '0';
            bittimer <= 0;
            if(rx_i = '0') then
                state <= S_START;
            end if;

        when S_START =>
            if (bittimer = c_bittimerlim/2 -1) then
                state <= S_DATA;
                bittimer <= 0;
            else 
                bittimer <= bittimer + 1;
            end if;

        when S_DATA =>
            if(bittimer = c_bittimerlim -1) then 
                if(bitcntr = 7 ) then 
                    state <= S_STOP;
                    bitcntr <= 0;
                else
                    bitcntr <= bitcntr + 1;
                end if;
                shreg <= rx_i & (shreg(7 downto 1));
                bittimer <= 0;
            else 
                bittimer <= bittimer + 1;
            end if;

        when S_STOP =>
            if (bittimer = c_bittimerlim -1) then
                state <= S_IDLE;
                bittimer <= 0;
                rx_done_tick_o <= '1';
            else 
                bittimer <= bittimer + 1;
            end if;
    end case;

    end if;

end process P_MAIN;

data_o <= shreg;

end Behavioral;

uart/uart_rx/src/tb_uart_rx.vhd
library IEEE;
use IEEE.STD_LOGIC_1164.ALL;


entity tb_uart_rx is
generic (
c_clkfreq		: integer := 100_000_000; -- System clock frequency (Hz)
c_baudrate		: integer := 115200 -- Serial communication baud rate (bps)
);
end tb_uart_rx;

architecture Behavioral of tb_uart_rx is
-- Testbench signals
signal clk             : std_logic := '0'; -- clock signal
signal rx_i            : std_logic := '1'; -- RX line (idle state is '1')
signal data_o          : std_logic_vector(7 downto 0); -- data output from DUT
signal rx_done_tick_o  : std_logic; -- RX done tick output from DUT

-- Time constants (for the test)
constant c_clkperiod : time := 10 ns; -- 100 MHz clock period
constant c_baud11520 : time := 8.68 us; -- time for one bit at 115200 baud (1/115200 seconds)

-- Example frames: start-bit = '1' + data(8 bit) + stop-bit = '0' (defined for test)
-- Note: here c_hex43 and c_hexA5 are defined as 10-bit vectors (start+8bit+stop)
constant c_hex43 : std_logic_vector(9 downto 0) := '1' & x"43" & '0';
constant c_hexA5 : std_logic_vector(9 downto 0) := '1' & x"A5" & '0';           

begin

DUT : entity work.uart_rx
generic map(
    c_clkfreq   => c_clkfreq,
    c_baudrate  => c_baudrate
)
port map(
    clk             => clk,
    rx_i            => rx_i,
    data_o          => data_o,
    rx_done_tick_o  => rx_done_tick_o
);

-- Clock generator: produces continuous square wave
P_CLKGEN : process begin

clk	<= '0';
wait for c_clkperiod/2;
clk	<= '1';
wait for c_clkperiod/2;

end process P_CLKGEN;

-- Stimulus: write example data frames to the RX line
P_STIMULI : process begin

wait for 1 us; -- initial wait before starting stimuli

-- first frame: send bits of c_hex43 sequentially
for i in 0 to 9 loop 
    rx_i <= c_hex43(i);
    wait for c_baud11520;
end loop;

wait for 10 us; -- gap between frames

-- second frame: send bits of c_hexA5 sequentially
for i in 0 to 9 loop 
    rx_i <= c_hexA5(i);
    wait for c_baud11520;
end loop;

wait for 20 us; -- wait before ending simulation

-- Use an assertion to terminate the simulation intentionally
assert false
report "SIM DONE"
severity failure;

end process P_STIMULI;


end Behavioral;

uart/uart_rx/src/uart_rx.vcd
$date
  Sat Feb 14 00:09:12 2026
$end
$version
  GHDL v0
$end
$timescale
  1 fs
$end
$scope module standard $end
$upscope $end
$scope module std_logic_1164 $end
$upscope $end
$scope module tb_uart_rx $end
$var reg 1 ! clk $end
$var reg 1 " rx_i $end
$var reg 8 # data_o[7:0] $end
$var reg 1 $ rx_done_tick_o $end
$scope module dut $end
$var reg 1 % clk $end
$var reg 1 & rx_i $end
$var reg 8 ' data_o[7:0] $end
$var reg 1 ( rx_done_tick_o $end
$comment state is not handled $end
$var integer 32 ) bittimer $end
$var integer 32 * bitcntr $end
$var reg 8 + shreg[7:0] $end
$upscope $end
$upscope $end
$enddefinitions $end
#0
0!
1"
b00000000 #
U$
0%
1&
b00000000 '
U(
b0 )
b0 *
b00000000 +
#5000000
1!
0$
1%
0(
#10000000
0!
0%
#15000000
1!
1%
#20000000
0!
0%
#25000000
1!
1%
#30000000
0!
0%
#35000000
1!
1%
#40000000
0!
0%
#45000000
1!
1%
#50000000
0!
0%
#55000000
1!
1%
#60000000
0!
0%
#65000000
1!
1%
#70000000
0!
0%
#75000000
1!
1%
#80000000
0!
0%
#85000000
1!
1%
#90000000
0!
0%
#95000000
1!
1%
#100000000
0!
0%
#105000000
1!
1%
#110000000
0!
0%
#115000000
1!
1%
#120000000
0!
0%
#125000000
1!
1%
#130000000
0!
0%
#135000000
1!
1%
#140000000
0!
0%
#145000000
1!
1%
#150000000
0!
0%
#155000000
1!
1%
#160000000
0!
0%
#165000000
1!
1%
#170000000
0!
0%
#175000000
1!
1%
#180000000
0!
0%
#185000000
1!
1%
#190000000
0!
0%
#195000000
1!
1%
#200000000
0!
0%
#205000000
1!
1%
#210000000
0!
0%
#215000000
1!
1%
#220000000
0!
0%
#225000000
1!
1%
#230000000
0!
0%
#235000000
1!
1%
#240000000
0!
0%
#245000000
1!
1%
#250000000
0!
0%
#255000000
1!
1%
#260000000
0!
0%
#265000000
1!
1%
#270000000
0!
0%
#275000000
1!
1%
#280000000
0!
0%
#285000000
1!
1%
#290000000
0!
0%
#295000000
1!
1%
#300000000
0!
0%
#305000000
1!
1%
#310000000
0!
0%
#315000000
1!
1%
#320000000
0!
0%
#325000000
1!
1%
#330000000
0!
0%
#335000000
1!
1%
#340000000
0!
0%
#345000000
1!
1%
#350000000
0!
0%
#355000000
1!
1%
#360000000
0!
0%
#365000000
1!
1%
#370000000
0!
0%
#375000000
1!
1%
#380000000
0!
0%
#385000000
1!
1%
#390000000
0!
0%
#395000000
1!
1%
#400000000
0!
0%
#405000000
1!
1%
#410000000
0!
0%
#415000000
1!
1%
#420000000
0!
0%
#425000000
1!
1%
#430000000
0!
0%
#435000000
1!
1%
#440000000
0!
0%
#445000000
1!
1%
#450000000
0!
0%
#455000000
1!
1%
#460000000
0!
0%
#465000000
1!
1%
#470000000
0!
0%
#475000000
1!
1%
#480000000
0!
0%
#485000000
1!
1%
#490000000
0!
0%
#495000000
1!
1%
#500000000
0!
0%
#505000000
1!
1%
#510000000
0!
0%
#515000000
1!
1%
#520000000
0!
0%
#525000000
1!
1%
#530000000
0!
0%
#535000000
1!
1%
#540000000
0!
0%
#545000000
1!
1%
#550000000
0!
0%
#555000000
1!
1%
#560000000
0!
0%
#565000000
1!
1%
#570000000
0!
0%
#575000000
1!
1%
#580000000
0!
0%
#585000000
1!
1%
#590000000
0!
0%
#595000000
1!
1%
#600000000
0!
0%
#605000000
1!
1%
#610000000
0!
0%
#615000000
1!
1%
#620000000
0!
0%
#625000000
1!
1%
#630000000
0!
0%
#635000000
1!
1%
#640000000
0!
0%
#645000000
1!
1%
#650000000
0!
0%
#655000000
1!
1%
#660000000
0!
0%
#665000000
1!
1%
#670000000
0!
0%
#675000000
1!
1%
#680000000
0!
0%
#685000000
1!
1%
#690000000
0!
0%
#695000000
1!
1%
#700000000
0!
0%
#705000000
1!
1%
#710000000
0!
0%
#715000000
1!
1%
#720000000
0!
0%
#725000000
1!
1%
#730000000
0!
0%
#735000000
1!
1%
#740000000
0!
0%
#745000000
1!
1%
#750000000
0!
0%
#755000000
1!
1%
#760000000
0!
0%
#765000000
1!
1%
#770000000
0!
0%
#775000000
1!
1%
#780000000
0!
0%
#785000000
1!
1%
#790000000
0!
0%
#795000000
1!
1%
#800000000
0!
0%
#805000000
1!
1%
#810000000
0!
0%
#815000000
1!
1%
#820000000
0!
0%
#825000000
1!
1%
#830000000
0!
0%
#835000000
1!
1%
#840000000
0!
0%
#845000000
1!
1%
#850000000
0!
0%
#855000000
1!
1%
#860000000
0!
0%
#865000000
1!
1%
#870000000
0!
0%
#875000000
1!
1%
#880000000
0!
0%
#885000000
1!
1%
#890000000
0!
0%
#895000000
1!
1%
#900000000
0!
0%
#905000000
1!
1%
#910000000
0!
0%
#915000000
1!
1%
#920000000
0!
0%
#925000000
1!
1%
#930000000
0!
0%
#935000000
1!
1%
#940000000
0!
0%
#945000000
1!
1%
#950000000
0!
0%
#955000000
1!
1%
#960000000
0!
0%
#965000000
1!
1%
#970000000
0!
0%
#975000000
1!
1%
#980000000
0!
0%
#985000000
1!
1%
#990000000
0!
0%
#995000000
1!
1%
#1000000000
0!
0"
0%
0&
#1005000000
1!
1%
#1010000000
0!
0%
#1015000000
1!
1%
b1 )
#1020000000
0!
0%
#1025000000
1!
1%
b10 )
#1030000000
0!
0%
#1035000000
1!
1%
b11 )
#1040000000
0!
0%
#1045000000
1!
1%
b100 )
#1050000000
0!
0%
#1055000000
1!
1%
b101 )
#1060000000
0!
0%
#1065000000
1!
1%
b110 )
#1070000000
0!
0%
#1075000000
1!
1%
b111 )
#1080000000
0!
0%
#1085000000
1!
1%
b1000 )
#1090000000
0!
0%
#1095000000
1!
1%
b1001 )
#1100000000
0!
0%
#1105000000
1!
1%
b1010 )
#1110000000
0!
0%
#1115000000
1!
1%
b1011 )
#1120000000
0!
0%
#1125000000
1!
1%
b1100 )
#1130000000
0!
0%
#1135000000
1!
1%
b1101 )
#1140000000
0!
0%
#1145000000
1!
1%
b1110 )
#1150000000
0!
0%
#1155000000
1!
1%
b1111 )
#1160000000
0!
0%
#1165000000
1!
1%
b10000 )
#1170000000
0!
0%
#1175000000
1!
1%
b10001 )
#1180000000
0!
0%
#1185000000
1!
1%
b10010 )
#1190000000
0!
0%
#1195000000
1!
1%
b10011 )
#1200000000
0!
0%
#1205000000
1!
1%
b10100 )
#1210000000
0!
0%
#1215000000
1!
1%
b10101 )
#1220000000
0!
0%
#1225000000
1!
1%
b10110 )
#1230000000
0!
0%
#1235000000
1!
1%
b10111 )
#1240000000
0!
0%
#1245000000
1!
1%
b11000 )
#1250000000
0!
0%
#1255000000
1!
1%
b11001 )
#1260000000
0!
0%
#1265000000
1!
1%
b11010 )
#1270000000
0!
0%
#1275000000
1!
1%
b11011 )
#1280000000
0!
0%
#1285000000
1!
1%
b11100 )
#1290000000
0!
0%
#1295000000
1!
1%
b11101 )
#1300000000
0!
0%
#1305000000
1!
1%
b11110 )
#1310000000
0!
0%
#1315000000
1!
1%
b11111 )
#1320000000
0!
0%
#1325000000
1!
1%
b100000 )
#1330000000
0!
0%
#1335000000
1!
1%
b100001 )
#1340000000
0!
0%
#1345000000
1!
1%
b100010 )
#1350000000
0!
0%
#1355000000
1!
1%
b100011 )
#1360000000
0!
0%
#1365000000
1!
1%
b100100 )
#1370000000
0!
0%
#1375000000
1!
1%
b100101 )
#1380000000
0!
0%
#1385000000
1!
1%
b100110 )
#1390000000
0!
0%
#1395000000
1!
1%
b100111 )
#1400000000
0!
0%
#1405000000
1!
1%
b101000 )
#1410000000
0!
0%
#1415000000
1!
1%
b101001 )
#1420000000
0!
0%
#1425000000
1!
1%
b101010 )
#1430000000
0!
0%
#1435000000
1!
1%
b101011 )
#1440000000
0!
0%
#1445000000
1!
1%
b101100 )
#1450000000
0!
0%
#1455000000
1!
1%
b101101 )
#1460000000
0!
0%
#1465000000
1!
1%
b101110 )
#1470000000
0!
0%
#1475000000
1!
1%
b101111 )
#1480000000
0!
0%
#1485000000
1!
1%
b110000 )
#1490000000
0!
0%
#1495000000
1!
1%
b110001 )
#1500000000
0!
0%
#1505000000
1!
1%
b110010 )
#1510000000
0!
0%
#1515000000
1!
1%
b110011 )
#1520000000
0!
0%
#1525000000
1!
1%
b110100 )
#1530000000
0!
0%
#1535000000
1!
1%
b110101 )
#1540000000
0!
0%
#1545000000
1!
1%
b110110 )
#1550000000
0!
0%
#1555000000
1!
1%
b110111 )
#1560000000
0!
0%
#1565000000
1!
1%
b111000 )
#1570000000
0!
0%
#1575000000
1!
1%
b111001 )
#1580000000
0!
0%
#1585000000
1!
1%
b111010 )
#1590000000
0!
0%
#1595000000
1!
1%
b111011 )
#1600000000
0!
0%
#1605000000
1!
1%
b111100 )
#1610000000
0!
0%
#1615000000
1!
1%
b111101 )
#1620000000
0!
0%
#1625000000
1!
1%
b111110 )
#1630000000
0!
0%
#1635000000
1!
1%
b111111 )
#1640000000
0!
0%
#1645000000
1!
1%
b1000000 )
#1650000000
0!
0%
#1655000000
1!
1%
b1000001 )
#1660000000
0!
0%
#1665000000
1!
1%
b1000010 )
#1670000000
0!
0%
#1675000000
1!
1%
b1000011 )
#1680000000
0!
0%
#1685000000
1!
1%
b1000100 )
#1690000000
0!
0%
#1695000000
1!
1%
b1000101 )
#1700000000
0!
0%
#1705000000
1!
1%
b1000110 )
#1710000000
0!
0%
#1715000000
1!
1%
b1000111 )
#1720000000
0!
0%
#1725000000
1!
1%
b1001000 )
#1730000000
0!
0%
#1735000000
1!
1%
b1001001 )
#1740000000
0!
0%
#1745000000
1!
1%
b1001010 )
#1750000000
0!
0%
#1755000000
1!
1%
b1001011 )
#1760000000
0!
0%
#1765000000
1!
1%
b1001100 )
#1770000000
0!
0%
#1775000000
1!
1%
b1001101 )
#1780000000
0!
0%
#1785000000
1!
1%
b1001110 )
#1790000000
0!
0%
#1795000000
1!
1%
b1001111 )
#1800000000
0!
0%
#1805000000
1!
1%
b1010000 )
#1810000000
0!
0%
#1815000000
1!
1%
b1010001 )
#1820000000
0!
0%
#1825000000
1!
1%
b1010010 )
#1830000000
0!
0%
#1835000000
1!
1%
b1010011 )
#1840000000
0!
0%
#1845000000
1!
1%
b1010100 )
#1850000000
0!
0%
#1855000000
1!
1%
b1010101 )
#1860000000
0!
0%
#1865000000
1!
1%
b1010110 )
#1870000000
0!
0%
#1875000000
1!
1%
b1010111 )
#1880000000
0!
0%
#1885000000
1!
1%
b1011000 )
#1890000000
0!
0%
#1895000000
1!
1%
b1011001 )
#1900000000
0!
0%
#1905000000
1!
1%
b1011010 )
#1910000000
0!
0%
#1915000000
1!
1%
b1011011 )
#1920000000
0!
0%
#1925000000
1!
1%
b1011100 )
#1930000000
0!
0%
#1935000000
1!
1%
b1011101 )
#1940000000
0!
0%
#1945000000
1!
1%
b1011110 )
#1950000000
0!
0%
#1955000000
1!
1%
b1011111 )
#1960000000
0!
0%
#1965000000
1!
1%
b1100000 )
#1970000000
0!
0%
#1975000000
1!
1%
b1100001 )
#1980000000
0!
0%
#1985000000
1!
1%
b1100010 )
#1990000000
0!
0%
#1995000000
1!
1%
b1100011 )
#2000000000
0!
0%
#2005000000
1!
1%
b1100100 )
#2010000000
0!
0%
#2015000000
1!
1%
b1100101 )
#2020000000
0!
0%
#2025000000
1!
1%
b1100110 )
#2030000000
0!
0%
#2035000000
1!
1%
b1100111 )
#2040000000
0!
0%
#2045000000
1!
1%
b1101000 )
#2050000000
0!
0%
#2055000000
1!
1%
b1101001 )
#2060000000
0!
0%
#2065000000
1!
1%
b1101010 )
#2070000000
0!
0%
#2075000000
1!
1%
b1101011 )
#2080000000
0!
0%
#2085000000
1!
1%
b1101100 )
#2090000000
0!
0%
#2095000000
1!
1%
b1101101 )
#2100000000
0!
0%
#2105000000
1!
1%
b1101110 )
#2110000000
0!
0%
#2115000000
1!
1%
b1101111 )
#2120000000
0!
0%
#2125000000
1!
1%
b1110000 )
#2130000000
0!
0%
#2135000000
1!
1%
b1110001 )
#2140000000
0!
0%
#2145000000
1!
1%
b1110010 )
#2150000000
0!
0%
#2155000000
1!
1%
b1110011 )
#2160000000
0!
0%
#2165000000
1!
1%
b1110100 )
#2170000000
0!
0%
#2175000000
1!
1%
b1110101 )
#2180000000
0!
0%
#2185000000
1!
1%
b1110110 )
#2190000000
0!
0%
#2195000000
1!
1%
b1110111 )
#2200000000
0!
0%
#2205000000
1!
1%
b1111000 )
#2210000000
0!
0%
#2215000000
1!
1%
b1111001 )
#2220000000
0!
0%
#2225000000
1!
1%
b1111010 )
#2230000000
0!
0%
#2235000000
1!
1%
b1111011 )
#2240000000
0!
0%
#2245000000
1!
1%
b1111100 )
#2250000000
0!
0%
#2255000000
1!
1%
b1111101 )
#2260000000
0!
0%
#2265000000
1!
1%
b1111110 )
#2270000000
0!
0%
#2275000000
1!
1%
b1111111 )
#2280000000
0!
0%
#2285000000
1!
1%
b10000000 )
#2290000000
0!
0%
#2295000000
1!
1%
b10000001 )
#2300000000
0!
0%
#2305000000
1!
1%
b10000010 )
#2310000000
0!
0%
#2315000000
1!
1%
b10000011 )
#2320000000
0!
0%
#2325000000
1!
1%
b10000100 )
#2330000000
0!
0%
#2335000000
1!
1%
b10000101 )
#2340000000
0!
0%
#2345000000
1!
1%
b10000110 )
#2350000000
0!
0%
#2355000000
1!
1%
b10000111 )
#2360000000
0!
0%
#2365000000
1!
1%
b10001000 )
#2370000000
0!
0%
#2375000000
1!
1%
b10001001 )
#2380000000
0!
0%
#2385000000
1!
1%
b10001010 )
#2390000000
0!
0%
#2395000000
1!
1%
b10001011 )
#2400000000
0!
0%
#2405000000
1!
1%
b10001100 )
#2410000000
0!
0%
#2415000000
1!
1%
b10001101 )
#2420000000
0!
0%
#2425000000
1!
1%
b10001110 )
#2430000000
0!
0%
#2435000000
1!
1%
b10001111 )
#2440000000
0!
0%
#2445000000
1!
1%
b10010000 )
#2450000000
0!
0%
#2455000000
1!
1%
b10010001 )
#2460000000
0!
0%
#2465000000
1!
1%
b10010010 )
#2470000000
0!
0%
#2475000000
1!
1%
b10010011 )
#2480000000
0!
0%
#2485000000
1!
1%
b10010100 )
#2490000000
0!
0%
#2495000000
1!
1%
b10010101 )
#2500000000
0!
0%
#2505000000
1!
1%
b10010110 )
#2510000000
0!
0%
#2515000000
1!
1%
b10010111 )
#2520000000
0!
0%
#2525000000
1!
1%
b10011000 )
#2530000000
0!
0%
#2535000000
1!
1%
b10011001 )
#2540000000
0!
0%
#2545000000
1!
1%
b10011010 )
#2550000000
0!
0%
#2555000000
1!
1%
b10011011 )
#2560000000
0!
0%
#2565000000
1!
1%
b10011100 )
#2570000000
0!
0%
#2575000000
1!
1%
b10011101 )
#2580000000
0!
0%
#2585000000
1!
1%
b10011110 )
#2590000000
0!
0%
#2595000000
1!
1%
b10011111 )
#2600000000
0!
0%
#2605000000
1!
1%
b10100000 )
#2610000000
0!
0%
#2615000000
1!
1%
b10100001 )
#2620000000
0!
0%
#2625000000
1!
1%
b10100010 )
#2630000000
0!
0%
#2635000000
1!
1%
b10100011 )
#2640000000
0!
0%
#2645000000
1!
1%
b10100100 )
#2650000000
0!
0%
#2655000000
1!
1%
b10100101 )
#2660000000
0!
0%
#2665000000
1!
1%
b10100110 )
#2670000000
0!
0%
#2675000000
1!
1%
b10100111 )
#2680000000
0!
0%
#2685000000
1!
1%
b10101000 )
#2690000000
0!
0%
#2695000000
1!
1%
b10101001 )
#2700000000
0!
0%
#2705000000
1!
1%
b10101010 )
#2710000000
0!
0%
#2715000000
1!
1%
b10101011 )
#2720000000
0!
0%
#2725000000
1!
1%
b10101100 )
#2730000000
0!
0%
#2735000000
1!
1%
b10101101 )
#2740000000
0!
0%
#2745000000
1!
1%
b10101110 )
#2750000000
0!
0%
#2755000000
1!
1%
b10101111 )
#2760000000
0!
0%
#2765000000
1!
1%
b10110000 )
#2770000000
0!
0%
#2775000000
1!
1%
b10110001 )
#2780000000
0!
0%
#2785000000
1!
1%
b10110010 )
#2790000000
0!
0%
#2795000000
1!
1%
b10110011 )
#2800000000
0!
0%
#2805000000
1!
1%
b10110100 )
#2810000000
0!
0%
#2815000000
1!
1%
b10110101 )
#2820000000
0!
0%
#2825000000
1!
1%
b10110110 )
#2830000000
0!
0%
#2835000000
1!
1%
b10110111 )
#2840000000
0!
0%
#2845000000
1!
1%
b10111000 )
#2850000000
0!
0%
#2855000000
1!
1%
b10111001 )
#2860000000
0!
0%
#2865000000
1!
1%
b10111010 )
#2870000000
0!
0%
#2875000000
1!
1%
b10111011 )
#2880000000
0!
0%
#2885000000
1!
1%
b10111100 )
#2890000000
0!
0%
#2895000000
1!
1%
b10111101 )
#2900000000
0!
0%
#2905000000
1!
1%
b10111110 )
#2910000000
0!
0%
#2915000000
1!
1%
b10111111 )
#2920000000
0!
0%
#2925000000
1!
1%
b11000000 )
#2930000000
0!
0%
#2935000000
1!
1%
b11000001 )
#2940000000
0!
0%
#2945000000
1!
1%
b11000010 )
#2950000000
0!
0%
#2955000000
1!
1%
b11000011 )
#2960000000
0!
0%
#2965000000
1!
1%
b11000100 )
#2970000000
0!
0%
#2975000000
1!
1%
b11000101 )
#2980000000
0!
0%
#2985000000
1!
1%
b11000110 )
#2990000000
0!
0%
#2995000000
1!
1%
b11000111 )
#3000000000
0!
0%
#3005000000
1!
1%
b11001000 )
#3010000000
0!
0%
#3015000000
1!
1%
b11001001 )
#3020000000
0!
0%
#3025000000
1!
1%
b11001010 )
#3030000000
0!
0%
#3035000000
1!
1%
b11001011 )
#3040000000
0!
0%
#3045000000
1!
1%
b11001100 )
#3050000000
0!
0%
#3055000000
1!
1%
b11001101 )
#3060000000
0!
0%
#3065000000
1!
1%
b11001110 )
#3070000000
0!
0%
#3075000000
1!
1%
b11001111 )
#3080000000
0!
0%
#3085000000
1!
1%
b11010000 )
#3090000000
0!
0%
#3095000000
1!
1%
b11010001 )
#3100000000
0!
0%
#3105000000
1!
1%
b11010010 )
#3110000000
0!
0%
#3115000000
1!
1%
b11010011 )
#3120000000
0!
0%
#3125000000
1!
1%
b11010100 )
#3130000000
0!
0%
#3135000000
1!
1%
b11010101 )
#3140000000
0!
0%
#3145000000
1!
1%
b11010110 )
#3150000000
0!
0%
#3155000000
1!
1%
b11010111 )
#3160000000
0!
0%
#3165000000
1!
1%
b11011000 )
#3170000000
0!
0%
#3175000000
1!
1%
b11011001 )
#3180000000
0!
0%
#3185000000
1!
1%
b11011010 )
#3190000000
0!
0%
#3195000000
1!
1%
b11011011 )
#3200000000
0!
0%
#3205000000
1!
1%
b11011100 )
#3210000000
0!
0%
#3215000000
1!
1%
b11011101 )
#3220000000
0!
0%
#3225000000
1!
1%
b11011110 )
#3230000000
0!
0%
#3235000000
1!
1%
b11011111 )
#3240000000
0!
0%
#3245000000
1!
1%
b11100000 )
#3250000000
0!
0%
#3255000000
1!
1%
b11100001 )
#3260000000
0!
0%
#3265000000
1!
1%
b11100010 )
#3270000000
0!
0%
#3275000000
1!
1%
b11100011 )
#3280000000
0!
0%
#3285000000
1!
1%
b11100100 )
#3290000000
0!
0%
#3295000000
1!
1%
b11100101 )
#3300000000
0!
0%
#3305000000
1!
1%
b11100110 )
#3310000000
0!
0%
#3315000000
1!
1%
b11100111 )
#3320000000
0!
0%
#3325000000
1!
1%
b11101000 )
#3330000000
0!
0%
#3335000000
1!
1%
b11101001 )
#3340000000
0!
0%
#3345000000
1!
1%
b11101010 )
#3350000000
0!
0%
#3355000000
1!
1%
b11101011 )
#3360000000
0!
0%
#3365000000
1!
1%
b11101100 )
#3370000000
0!
0%
#3375000000
1!
1%
b11101101 )
#3380000000
0!
0%
#3385000000
1!
1%
b11101110 )
#3390000000
0!
0%
#3395000000
1!
1%
b11101111 )
#3400000000
0!
0%
#3405000000
1!
1%
b11110000 )
#3410000000
0!
0%
#3415000000
1!
1%
b11110001 )
#3420000000
0!
0%
#3425000000
1!
1%
b11110010 )
#3430000000
0!
0%
#3435000000
1!
1%
b11110011 )
#3440000000
0!
0%
#3445000000
1!
1%
b11110100 )
#3450000000
0!
0%
#3455000000
1!
1%
b11110101 )
#3460000000
0!
0%
#3465000000
1!
1%
b11110110 )
#3470000000
0!
0%
#3475000000
1!
1%
b11110111 )
#3480000000
0!
0%
#3485000000
1!
1%
b11111000 )
#3490000000
0!
0%
#3495000000
1!
1%
b11111001 )
#3500000000
0!
0%
#3505000000
1!
1%
b11111010 )
#3510000000
0!
0%
#3515000000
1!
1%
b11111011 )
#3520000000
0!
0%
#3525000000
1!
1%
b11111100 )
#3530000000
0!
0%
#3535000000
1!
1%
b11111101 )
#3540000000
0!
0%
#3545000000
1!
1%
b11111110 )
#3550000000
0!
0%
#3555000000
1!
1%
b11111111 )
#3560000000
0!
0%
#3565000000
1!
1%
b100000000 )
#3570000000
0!
0%
#3575000000
1!
1%
b100000001 )
#3580000000
0!
0%
#3585000000
1!
1%
b100000010 )
#3590000000
0!
0%
#3595000000
1!
1%
b100000011 )
#3600000000
0!
0%
#3605000000
1!
1%
b100000100 )
#3610000000
0!
0%
#3615000000
1!
1%
b100000101 )
#3620000000
0!
0%
#3625000000
1!
1%
b100000110 )
#3630000000
0!
0%
#3635000000
1!
1%
b100000111 )
#3640000000
0!
0%
#3645000000
1!
1%
b100001000 )
#3650000000
0!
0%
#3655000000
1!
1%
b100001001 )
#3660000000
0!
0%
#3665000000
1!
1%
b100001010 )
#3670000000
0!
0%
#3675000000
1!
1%
b100001011 )
#3680000000
0!
0%
#3685000000
1!
1%
b100001100 )
#3690000000
0!
0%
#3695000000
1!
1%
b100001101 )
#3700000000
0!
0%
#3705000000
1!
1%
b100001110 )
#3710000000
0!
0%
#3715000000
1!
1%
b100001111 )
#3720000000
0!
0%
#3725000000
1!
1%
b100010000 )
#3730000000
0!
0%
#3735000000
1!
1%
b100010001 )
#3740000000
0!
0%
#3745000000
1!
1%
b100010010 )
#3750000000
0!
0%
#3755000000
1!
1%
b100010011 )
#3760000000
0!
0%
#3765000000
1!
1%
b100010100 )
#3770000000
0!
0%
#3775000000
1!
1%
b100010101 )
#3780000000
0!
0%
#3785000000
1!
1%
b100010110 )
#3790000000
0!
0%
#3795000000
1!
1%
b100010111 )
#3800000000
0!
0%
#3805000000
1!
1%
b100011000 )
#3810000000
0!
0%
#3815000000
1!
1%
b100011001 )
#3820000000
0!
0%
#3825000000
1!
1%
b100011010 )
#3830000000
0!
0%
#3835000000
1!
1%
b100011011 )
#3840000000
0!
0%
#3845000000
1!
1%
b100011100 )
#3850000000
0!
0%
#3855000000
1!
1%
b100011101 )
#3860000000
0!
0%
#3865000000
1!
1%
b100011110 )
#3870000000
0!
0%
#3875000000
1!
1%
b100011111 )
#3880000000
0!
0%
#3885000000
1!
1%
b100100000 )
#3890000000
0!
0%
#3895000000
1!
1%
b100100001 )
#3900000000
0!
0%
#3905000000
1!
1%
b100100010 )
#3910000000
0!
0%
#3915000000
1!
1%
b100100011 )
#3920000000
0!
0%
#3925000000
1!
1%
b100100100 )
#3930000000
0!
0%
#3935000000
1!
1%
b100100101 )
#3940000000
0!
0%
#3945000000
1!
1%
b100100110 )
#3950000000
0!
0%
#3955000000
1!
1%
b100100111 )
#3960000000
0!
0%
#3965000000
1!
1%
b100101000 )
#3970000000
0!
0%
#3975000000
1!
1%
b100101001 )
#3980000000
0!
0%
#3985000000
1!
1%
b100101010 )
#3990000000
0!
0%
#3995000000
1!
1%
b100101011 )
#4000000000
0!
0%
#4005000000
1!
1%
b100101100 )
#4010000000
0!
0%
#4015000000
1!
1%
b100101101 )
#4020000000
0!
0%
#4025000000
1!
1%
b100101110 )
#4030000000
0!
0%
#4035000000
1!
1%
b100101111 )
#4040000000
0!
0%
#4045000000
1!
1%
b100110000 )
#4050000000
0!
0%
#4055000000
1!
1%
b100110001 )
#4060000000
0!
0%
#4065000000
1!
1%
b100110010 )
#4070000000
0!
0%
#4075000000
1!
1%
b100110011 )
#4080000000
0!
0%
#4085000000
1!
1%
b100110100 )
#4090000000
0!
0%
#4095000000
1!
1%
b100110101 )
#4100000000
0!
0%
#4105000000
1!
1%
b100110110 )
#4110000000
0!
0%
#4115000000
1!
1%
b100110111 )
#4120000000
0!
0%
#4125000000
1!
1%
b100111000 )
#4130000000
0!
0%
#4135000000
1!
1%
b100111001 )
#4140000000
0!
0%
#4145000000
1!
1%
b100111010 )
#4150000000
0!
0%
#4155000000
1!
1%
b100111011 )
#4160000000
0!
0%
#4165000000
1!
1%
b100111100 )
#4170000000
0!
0%
#4175000000
1!
1%
b100111101 )
#4180000000
0!
0%
#4185000000
1!
1%
b100111110 )
#4190000000
0!
0%
#4195000000
1!
1%
b100111111 )
#4200000000
0!
0%
#4205000000
1!
1%
b101000000 )
#4210000000
0!
0%
#4215000000
1!
1%
b101000001 )
#4220000000
0!
0%
#4225000000
1!
1%
b101000010 )
#4230000000
0!
0%
#4235000000
1!
1%
b101000011 )
#4240000000
0!
0%
#4245000000
1!
1%
b101000100 )
#4250000000
0!
0%
#4255000000
1!
1%
b101000101 )
#4260000000
0!
0%
#4265000000
1!
1%
b101000110 )
#4270000000
0!
0%
#4275000000
1!
1%
b101000111 )
#4280000000
0!
0%
#4285000000
1!
1%
b101001000 )
#4290000000
0!
0%
#4295000000
1!
1%
b101001001 )
#4300000000
0!
0%
#4305000000
1!
1%
b101001010 )
#4310000000
0!
0%
#4315000000
1!
1%
b101001011 )
#4320000000
0!
0%
#4325000000
1!
1%
b101001100 )
#4330000000
0!
0%
#4335000000
1!
1%
b101001101 )
#4340000000
0!
0%
#4345000000
1!
1%
b101001110 )
#4350000000
0!
0%
#4355000000
1!
1%
b101001111 )
#4360000000
0!
0%
#4365000000
1!
1%
b101010000 )
#4370000000
0!
0%
#4375000000
1!
1%
b101010001 )
#4380000000
0!
0%
#4385000000
1!
1%
b101010010 )
#4390000000
0!
0%
#4395000000
1!
1%
b101010011 )
#4400000000
0!
0%
#4405000000
1!
1%
b101010100 )
#4410000000
0!
0%
